Workbook

Sheet Raw Orders
A1: HOW TO USE: Whenever you export orders from your admin dashboard, paste just the data rows (not the header) starting in row 3 below, replacing what's here. Delete any "TOTAL" row from what you paste — the Month column (P) and the Monthly P&L sheet keep working automatically either way.
A2: Date | B2: Time | C2: Name | D2: Phone | E2: Base | F2: Cup Size | G2: Rim | H2: Toppings | I2: Syrup | J2: Qty | K2: Pickup Date | L2: Pickup Time | M2: Payment Method | N2: Paid | O2: Total | P2: Month | R2: All-time revenue in this sheet: | S2: =SUM(O3:O500) -> 65.8
A3: 9/26/2026 | B3: 2:55:11 AM | C3: Destiveth | E3: 1x Regular Fresas; 1x Regular Fresas | F3: 12 oz | H3: [Regular Fresas] Wafer Cookie, Whipped Cream, Oreo | [Regular Fresas] Whipped Cream, Fruity Pebbles, Almonds | I3: [Regular Fresas] Lechera | [Regular Fresas] Caramel, Nutella | J3: 2 | K3: 2026-09-25 | L3: 8:45 PM | M3: cash | N3: No | O3: 12.6 | P3: =IF($A3="","",IFERROR(TEXT(DATE(VALUE(RIGHT($A3,4)),VALUE(LEFT($A3,FIND("/",$A3)-1)),1),"mmm yyyy"),"")) -> Sep 2026
A4: 9/25/2026 | B4: 10:31:30 PM | C4: Katia Perez | D4: (909) 602-9681 | E4: 1x Ferrero Rocher; 1x Gansito | F4: 12 oz | G4: Gansito: Yes | H4: [Ferrero Rocher] Whipped Cream, Wafer Cookie | [Gansito] Whipped Cream, Wafer Cookie | I4: [Ferrero Rocher] Nutella | [Gansito] Chocolate | J4: 2 | K4: 2026-09-25 | L4: 5:00 PM | M4: cash | N4: No | O4: 16.2 | P4: =IF($A4="","",IFERROR(TEXT(DATE(VALUE(RIGHT($A4,4)),VALUE(LEFT($A4,FIND("/",$A4)-1)),1),"mmm yyyy"),"")) -> Sep 2026
A5: 9/25/2026 | B5: 9:55:13 PM | C5: Adrian | E5: 1x Gansito; 1x Banana Pudding | F5: 12 oz | G5: Gansito: Yes; Banana Pudding: Yes | H5: [Gansito] Cheesecake, Coconut Flakes, Almonds | [Banana Pudding] Whipped Cream, Almonds, Granola | I5: [Gansito] Nutella, Lechera | [Banana Pudding] Lechera | J5: 2 | K5: 2026-09-25 | L5: 5:00 PM | M5: zelle | N5: Yes | O5: 19 | P5: =IF($A5="","",IFERROR(TEXT(DATE(VALUE(RIGHT($A5,4)),VALUE(LEFT($A5,FIND("/",$A5)-1)),1),"mmm yyyy"),"")) -> Sep 2026
A6: 9/23/2026 | B6: 3:19:43 AM | C6: Nikki Nasty | D6: (951) 419-7358 | E6: Regular Fresas | F6: 12 oz | H6: Whipped Cream, Almonds, Coconut Flakes, Granola, Cheesecake | I6: Lechera, Nutella | J6: 2 | K6: 2026-09-22 | L6: 9:00 PM | M6: zelle | N6: Yes | O6: 18 | P6: =IF($A6="","",IFERROR(TEXT(DATE(VALUE(RIGHT($A6,4)),VALUE(LEFT($A6,FIND("/",$A6)-1)),1),"mmm yyyy"),"")) -> Sep 2026
P7: =IF($A7="","",IFERROR(TEXT(DATE(VALUE(RIGHT($A7,4)),VALUE(LEFT($A7,FIND("/",$A7)-1)),1),"mmm yyyy"),""))
P8: =IF($A8="","",IFERROR(TEXT(DATE(VALUE(RIGHT($A8,4)),VALUE(LEFT($A8,FIND("/",$A8)-1)),1),"mmm yyyy"),""))
P9: =IF($A9="","",IFERROR(TEXT(DATE(VALUE(RIGHT($A9,4)),VALUE(LEFT($A9,FIND("/",$A9)-1)),1),"mmm yyyy"),""))
P10: =IF($A10="","",IFERROR(TEXT(DATE(VALUE(RIGHT($A10,4)),VALUE(LEFT($A10,FIND("/",$A10)-1)),1),"mmm yyyy"),""))
P11: =IF($A11="","",IFERROR(TEXT(DATE(VALUE(RIGHT($A11,4)),VALUE(LEFT($A11,FIND("/",$A11)-1)),1),"mmm yyyy"),""))
P12: =IF($A12="","",IFERROR(TEXT(DATE(VALUE(RIGHT($A12,4)),VALUE(LEFT($A12,FIND("/",$A12)-1)),1),"mmm yyyy"),""))
P13: =IF($A13="","",IFERROR(TEXT(DATE(VALUE(RIGHT($A13,4)),VALUE(LEFT($A13,FIND("/",$A13)-1)),1),"mmm yyyy"),""))
P14: =IF($A14="","",IFERROR(TEXT(DATE(VALUE(RIGHT($A14,4)),VALUE(LEFT($A14,FIND("/",$A14)-1)),1),"mmm yyyy"),""))
P15: =IF($A15="","",IFERROR(TEXT(DATE(VALUE(RIGHT($A15,4)),VALUE(LEFT($A15,FIND("/",$A15)-1)),1),"mmm yyyy"),""))
P16: =IF($A16="","",IFERROR(TEXT(DATE(VALUE(RIGHT($A16,4)),VALUE(LEFT($A16,FIND("/",$A16)-1)),1),"mmm yyyy"),""))
P17: =IF($A17="","",IFERROR(TEXT(DATE(VALUE(RIGHT($A17,4)),VALUE(LEFT($A17,FIND("/",$A17)-1)),1),"mmm yyyy"),""))
P18: =IF($A18="","",IFERROR(TEXT(DATE(VALUE(RIGHT($A18,4)),VALUE(LEFT($A18,FIND("/",$A18)-1)),1),"mmm yyyy"),""))
... P500: =IF($A500="","",IFERROR(TEXT(DATE(VALUE(RIGHT($A500,4)),VALUE(LEFT($A500,FIND("/",$A500)-1)),1),"mmm yyyy"),""))

Sheet Expenses
A1: HOW TO USE: Add one row per expense — Date, Category (pick from the dropdown), a short Description, and the Amount. The yellow example row below shows the format; delete it once you start entering your own.
A2: Date | B2: Month | C2: Category | D2: Description | E2: Amount | G2: Categories:
A3: 9/24/2026 | B3: =IF($A3="","",TEXT($A3,"mmm yyyy")) -> Sep 2026 | C3: Ingredients | D3: [Example — delete this row] Strawberries, cream, chocolate from Costco | E3: 42.5 | G3: Ingredients
B4: =IF($A4="","",TEXT($A4,"mmm yyyy")) | G4: Toppings & Syrups
B5: =IF($A5="","",TEXT($A5,"mmm yyyy")) | G5: Cups & Packaging
B6: =IF($A6="","",TEXT($A6,"mmm yyyy")) | G6: Payment Processing Fees
B7: =IF($A7="","",TEXT($A7,"mmm yyyy")) | G7: Marketing & Promos
B8: =IF($A8="","",TEXT($A8,"mmm yyyy")) | G8: Supplies & Equipment
B9: =IF($A9="","",TEXT($A9,"mmm yyyy")) | G9: Delivery/Gas
B10: =IF($A10="","",TEXT($A10,"mmm yyyy")) | G10: Other
B11: =IF($A11="","",TEXT($A11,"mmm yyyy"))
B12: =IF($A12="","",TEXT($A12,"mmm yyyy"))
B13: =IF($A13="","",TEXT($A13,"mmm yyyy"))
B14: =IF($A14="","",TEXT($A14,"mmm yyyy"))
B15: =IF($A15="","",TEXT($A15,"mmm yyyy"))
B16: =IF($A16="","",TEXT($A16,"mmm yyyy"))
B17: =IF($A17="","",TEXT($A17,"mmm yyyy"))
B18: =IF($A18="","",TEXT($A18,"mmm yyyy"))
B19: =IF($A19="","",TEXT($A19,"mmm yyyy"))
B20: =IF($A20="","",TEXT($A20,"mmm yyyy"))
B21: =IF($A21="","",TEXT($A21,"mmm yyyy"))
B22: =IF($A22="","",TEXT($A22,"mmm yyyy"))
... B500: =IF($A500="","",TEXT($A500,"mmm yyyy"))

Sheet Monthly P&L
A1: This sheet updates itself from Raw Orders and Expenses — nothing to fill in here. If you're still tracking past December 2027, copy the last row's formulas down into a new row with the next month's name.
A2: Month | B2: Revenue | C2: Expenses | D2: Profit | E2: Profit Margin
A3: Sep 2026 | B3: =SUMIFS('Raw Orders'!$O$3:$O$500,'Raw Orders'!$P$3:$P$500,$A3) -> 65.8 | C3: =SUMIFS(Expenses!$E$3:$E$500,Expenses!$B$3:$B$500,$A3) -> 42.5 | D3: =B3-C3 -> 23.3 | E3: =IF(B3=0,"",D3/B3) -> 0.35410334
A4: Oct 2026 | B4: =SUMIFS('Raw Orders'!$O$3:$O$500,'Raw Orders'!$P$3:$P$500,$A4) -> 0 | C4: =SUMIFS(Expenses!$E$3:$E$500,Expenses!$B$3:$B$500,$A4) -> 0 | D4: =B4-C4 -> 0 | E4: =IF(B4=0,"",D4/B4)
A5: Nov 2026 | B5: =SUMIFS('Raw Orders'!$O$3:$O$500,'Raw Orders'!$P$3:$P$500,$A5) -> 0 | C5: =SUMIFS(Expenses!$E$3:$E$500,Expenses!$B$3:$B$500,$A5) -> 0 | D5: =B5-C5 -> 0 | E5: =IF(B5=0,"",D5/B5)
A6: Dec 2026 | B6: =SUMIFS('Raw Orders'!$O$3:$O$500,'Raw Orders'!$P$3:$P$500,$A6) -> 0 | C6: =SUMIFS(Expenses!$E$3:$E$500,Expenses!$B$3:$B$500,$A6) -> 0 | D6: =B6-C6 -> 0 | E6: =IF(B6=0,"",D6/B6)
A7: Jan 2027 | B7: =SUMIFS('Raw Orders'!$O$3:$O$500,'Raw Orders'!$P$3:$P$500,$A7) -> 0 | C7: =SUMIFS(Expenses!$E$3:$E$500,Expenses!$B$3:$B$500,$A7) -> 0 | D7: =B7-C7 -> 0 | E7: =IF(B7=0,"",D7/B7)
A8: Feb 2027 | B8: =SUMIFS('Raw Orders'!$O$3:$O$500,'Raw Orders'!$P$3:$P$500,$A8) -> 0 | C8: =SUMIFS(Expenses!$E$3:$E$500,Expenses!$B$3:$B$500,$A8) -> 0 | D8: =B8-C8 -> 0 | E8: =IF(B8=0,"",D8/B8)
A9: Mar 2027 | B9: =SUMIFS('Raw Orders'!$O$3:$O$500,'Raw Orders'!$P$3:$P$500,$A9) -> 0 | C9: =SUMIFS(Expenses!$E$3:$E$500,Expenses!$B$3:$B$500,$A9) -> 0 | D9: =B9-C9 -> 0 | E9: =IF(B9=0,"",D9/B9)
A10: Apr 2027 | B10: =SUMIFS('Raw Orders'!$O$3:$O$500,'Raw Orders'!$P$3:$P$500,$A10) -> 0 | C10: =SUMIFS(Expenses!$E$3:$E$500,Expenses!$B$3:$B$500,$A10) -> 0 | D10: =B10-C10 -> 0 | E10: =IF(B10=0,"",D10/B10)
A11: May 2027 | B11: =SUMIFS('Raw Orders'!$O$3:$O$500,'Raw Orders'!$P$3:$P$500,$A11) -> 0 | C11: =SUMIFS(Expenses!$E$3:$E$500,Expenses!$B$3:$B$500,$A11) -> 0 | D11: =B11-C11 -> 0 | E11: =IF(B11=0,"",D11/B11)
A12: Jun 2027 | B12: =SUMIFS('Raw Orders'!$O$3:$O$500,'Raw Orders'!$P$3:$P$500,$A12) -> 0 | C12: =SUMIFS(Expenses!$E$3:$E$500,Expenses!$B$3:$B$500,$A12) -> 0 | D12: =B12-C12 -> 0 | E12: =IF(B12=0,"",D12/B12)
A13: Jul 2027 | B13: =SUMIFS('Raw Orders'!$O$3:$O$500,'Raw Orders'!$P$3:$P$500,$A13) -> 0 | C13: =SUMIFS(Expenses!$E$3:$E$500,Expenses!$B$3:$B$500,$A13) -> 0 | D13: =B13-C13 -> 0 | E13: =IF(B13=0,"",D13/B13)
A14: Aug 2027 | B14: =SUMIFS('Raw Orders'!$O$3:$O$500,'Raw Orders'!$P$3:$P$500,$A14) -> 0 | C14: =SUMIFS(Expenses!$E$3:$E$500,Expenses!$B$3:$B$500,$A14) -> 0 | D14: =B14-C14 -> 0 | E14: =IF(B14=0,"",D14/B14)
... A18: Dec 2027 | B18: =SUMIFS('Raw Orders'!$O$3:$O$500,'Raw Orders'!$P$3:$P$500,$A18) -> 0 | C18: =SUMIFS(Expenses!$E$3:$E$500,Expenses!$B$3:$B$500,$A18) -> 0 | D18: =B18-C18 -> 0 | E18: =IF(B18=0,"",D18/B18)
A20: TOTAL | B20: =SUM(B3:B18) -> 65.8 | C20: =SUM(C3:C18) -> 42.5 | D20: =B20-C20 -> 23.3 | E20: =IF(B20=0,"",D20/B20) -> 0.35410334
